{
  "annotations": {
    "list": [
      {
        "builtIn": 1,
        "datasource": "-- Grafana --",
        "enable": true,
        "hide": true,
        "iconColor": "rgba(0, 211, 255, 1)",
        "name": "Annotations & Alerts",
        "type": "dashboard"
      }
    ]
  },
  "editable": true,
  "gnetId": null,
  "graphTooltip": 0,
  "id": 2,
  "links": [],
  "panels": [
    {
      "datasource": null,
      "fieldConfig": {
        "defaults": {
          "custom": {},
          "mappings": [],
          "thresholds": {
            "mode": "absolute",
            "steps": [
              {
                "color": "green",
                "value": null
              },
              {
                "color": "#EAB839",
                "value": 40
              },
              {
                "color": "red",
                "value": 60
              }
            ]
          }
        },
        "overrides": []
      },
      "gridPos": {
        "h": 11,
        "w": 24,
        "x": 0,
        "y": 0
      },
      "id": 2,
      "options": {
        "reduceOptions": {
          "calcs": [
            "mean"
          ],
          "fields": "",
          "values": false
        },
        "showThresholdLabels": true,
        "showThresholdMarkers": true
      },
      "pluginVersion": "7.3.1",
      "targets": [
        {
          "alias": "ServerA",
          "groupBy": [],
          "measurement": "cpu",
          "orderByTime": "ASC",
          "policy": "default",
          "refId": "A",
          "resultFormat": "time_series",
          "select": [
            [
              {
                "params": [
                  "value"
                ],
                "type": "field"
              }
            ]
          ],
          "tags": [
            {
              "key": "host",
              "operator": "=",
              "value": "serverA"
            }
          ]
        },
        {
          "alias": "ServerB",
          "groupBy": [],
          "measurement": "cpu",
          "orderByTime": "ASC",
          "policy": "default",
          "refId": "B",
          "resultFormat": "time_series",
          "select": [
            [
              {
                "params": [
                  "value"
                ],
                "type": "field"
              }
            ]
          ],
          "tags": [
            {
              "key": "host",
              "operator": "=",
              "value": "serverB"
            }
          ]
        },
        {
          "alias": "ServerC",
          "groupBy": [],
          "measurement": "cpu",
          "orderByTime": "ASC",
          "policy": "default",
          "refId": "C",
          "resultFormat": "time_series",
          "select": [
            [
              {
                "params": [
                  "value"
                ],
                "type": "field"
              }
            ]
          ],
          "tags": [
            {
              "key": "host",
              "operator": "=",
              "value": "serverC"
            }
          ]
        },
        {
          "alias": "ServerD",
          "groupBy": [],
          "measurement": "cpu",
          "orderByTime": "ASC",
          "policy": "default",
          "refId": "D",
          "resultFormat": "time_series",
          "select": [
            [
              {
                "params": [
                  "value"
                ],
                "type": "field"
              }
            ]
          ],
          "tags": [
            {
              "key": "host",
              "operator": "=",
              "value": "serverD"
            }
          ]
        },
        {
          "alias": "ServerE",
          "groupBy": [],
          "measurement": "cpu",
          "orderByTime": "ASC",
          "policy": "default",
          "refId": "E",
          "resultFormat": "time_series",
          "select": [
            [
              {
                "params": [
                  "value"
                ],
                "type": "field"
              }
            ]
          ],
          "tags": [
            {
              "key": "host",
              "operator": "=",
              "value": "serverE"
            }
          ]
        },
        {
          "alias": "ServerF",
          "groupBy": [],
          "measurement": "cpu",
          "orderByTime": "ASC",
          "policy": "default",
          "refId": "F",
          "resultFormat": "time_series",
          "select": [
            [
              {
                "params": [
                  "value"
                ],
                "type": "field"
              }
            ]
          ],
          "tags": [
            {
              "key": "host",
              "operator": "=",
              "value": "serverF"
            }
          ]
        }
      ],
      "timeFrom": null,
      "timeShift": null,
      "title": "Serveur monitoring",
      "type": "gauge"
    }
  ],
  "refresh": false,
  "schemaVersion": 26,
  "style": "dark",
  "tags": [],
  "templating": {
    "list": []
  },
  "time": {
    "from": "2020-02-19T17:14:12.512Z",
    "to": "2021-07-15T17:14:12.512Z"
  },
  "timepicker": {
    "refresh_intervals": [
      "30s"
    ]
  },
  "timezone": "",
  "title": "Server monitoring Exemple",
  "uid": "3MPqTnhGk",
  "version": 4
}